Digital Logic/Lab_1/23B1018_bcd_to_7_segment_behv.v
module seven_segment(
    input x1,
    input x2,
    input x3,
    input x4,
    output A, B, C, D, E, F, G
);

assign A = (x1|x2|x3|~x4)&(x1|~x2|x4) ;
assign B = (x1|~x2|x3|~x4)&(x1|~x2|~x3|x4) ;
assign C = x1|x2|~x3|x4 ;
assign D = (x2|x3|~x4)&(x1|~x2|x3|x4)&(x1|~x2|~x3|~x4) ;
assign E = (~x1&x3&~x4)|(~x2&~x3&~x4) ;
assign F = (x1|x2|~x4)&(x1|~x3|~x4)&(x1|x2|~x3) ; 
assign G = (x1|x2|x3|~x4)&(x1|~x2|~x3|~x4)&(x1|x2|x3|x4) ;

endmodule

Digital Logic/Lab_1/23B1018_tb_bcd_to_7_segment_behv.v
module testbench ;
    reg x1, x2, x3, x4 ;
    wire A, B, C, D, E, F, G ;

    seven_segment uut(
        .x1(x1),
        .x2(x2),
        .x3(x3),
        .x4(x4),
        .A(A),
        .B(B),
        .C(C),
        .D(D),
        .E(E),
        .F(F),
        .G(G)
    );

    initial begin
        // Create a dump file to get the wave form with gtkwave.
        $dumpfile("dump.vcd") ;
        // import all the variables you want in the wave form
        $dumpvars(0, testbench) ;

        // monitor the variables.
        $display("x1 x2 x3 x4 - A B C D E F G") ;
        $monitor("%b  %b  %b  %b    %b %b %b %b %b %b %b",x1, x2, x3, x4, A, B, C, D, E, F, G) ;

        x1 = 0; x2 = 0; x3 = 0; x4 = 1 ; #10;
        x1 = 0; x2 = 0; x3 = 1; x4 = 0 ; #10 ;
        x1 = 0; x2 = 0; x3 = 1; x4 = 1 ; #10 ;
        x1 = 0; x2 = 1; x3 = 0; x4 = 0 ; #10 ;
        x1 = 0; x2 = 1; x3 = 0; x4 = 1 ; #10 ;
        x1 = 0; x2 = 1; x3 = 1; x4 = 0 ; #10 ;
        x1 = 0; x2 = 1; x3 = 1; x4 = 1 ; #10 ;
        x1 = 1; x2 = 0; x3 = 0; x4 = 0 ; #10 ;
        x1 = 1; x2 = 0; x3 = 0; x4 = 1 ; #10 ;
        x1 = 0; x2 = 0; x3 = 0; x4 = 0 ; #10 ;

        $display("Name: Abhinav Chowdary Bikkina.") ; 
        $display("Roll_No : 23B1018") ;

        $finish ;
    end

endmodule

Digital Logic/Lab_1/dump.vcd
$date
	Tue Sep 24 01:38:40 2024
$end
$version
	Icarus Verilog
$end
$timescale
	1s
$end
$scope module testbench $end
$var wire 1 ! G $end
$var wire 1 " F $end
$var wire 1 # E $end
$var wire 1 $ D $end
$var wire 1 % C $end
$var wire 1 & B $end
$var wire 1 ' A $end
$var reg 1 ( x1 $end
$var reg 1 ) x2 $end
$var reg 1 * x3 $end
$var reg 1 + x4 $end
$scope module uut $end
$var wire 1 ' A $end
$var wire 1 & B $end
$var wire 1 % C $end
$var wire 1 $ D $end
$var wire 1 # E $end
$var wire 1 " F $end
$var wire 1 ! G $end
$var wire 1 ( x1 $end
$var wire 1 ) x2 $end
$var wire 1 * x3 $end
$var wire 1 + x4 $end
$upscope $end
$upscope $end
$enddefinitions $end
#0
$dumpvars
1+
0*
0)
0(
0'
1&
1%
0$
0#
0"
0!
$end
#10
1$
1!
1'
0%
1#
0+
1*
#20
0#
1%
1+
#30
0$
0'
1"
1%
0+
0*
1)
#40
0&
1$
1'
1+
#50
1#
0'
0+
1*
#60
0"
0!
0$
0#
1'
1&
1+
#70
1!
1"
1$
1#
1&
0+
0*
0)
1(
#80
0$
0#
1+
#90
1$
0!
1#
0+
0(
